LICENSE
MANIFEST.in
README.md
setup.cfg
setup.py
suapintegration/__init__.py
suapintegration/admin.py
suapintegration/backends.py
suapintegration/default_settings.py
suapintegration/models.py
suapintegration/urls.py
suapintegration.egg-info/PKG-INFO
suapintegration.egg-info/SOURCES.txt
suapintegration.egg-info/dependency_links.txt
suapintegration.egg-info/requires.txt
suapintegration.egg-info/top_level.txt
suapintegration/migrations/0001_initial.py
suapintegration/migrations/0002_auto_20201112_1407.py
suapintegration/migrations/__init__.py
suapintegration/migrations/__pycache__/0001_initial.cpython-38.pyc
suapintegration/migrations/__pycache__/0002_auto_20201112_1407.cpython-38.pyc
suapintegration/migrations/__pycache__/__init__.cpython-38.pyc