Metadata-Version: 1.1
Name: suapintegration
Version: 1.0.3
Summary: Utils and theme classes for SUAP-EAD project services
Home-page: https://github.com/suap-ead/lib_suapintegration
Author: Kelson da Costa Medeiros, Luiz Antonio Freitas de Assis
Author-email: kelsoncm@gmail.com, luizvpc@gmail.com
License: MIT
Download-URL: https://github.com/suap-ead/lib_suapintegration/releases/tag/1.0.3
Keywords: SUAP,EAD,complemento,oAuth2,Django,Auth,SSO,client,Theme
Platform: UNKNOWN
Classifier: Programming Language :: Python :: 3
Classifier: License :: OSI Approved :: MIT License
Classifier: Operating System :: OS Independent
